wdl_lsp/__init__.py
wdl_lsp/__main__.py
wdl_lsp/server.py
wdl_lsp/tests/__init__.py
wdl_lsp/tests/unit/__init__.py
wdl_lsp/tests/unit/test_features.py
wdl_lsp-0.0.90.dist-info/METADATA
wdl_lsp-0.0.90.dist-info/WHEEL
wdl_lsp-0.0.90.dist-info/entry_points.txt
wdl_lsp-0.0.90.dist-info/top_level.txt
wdl_lsp-0.0.90.dist-info/RECORD
