Metadata-Version: 2.1
Name: wdl-lsp
Version: 0.0.90
Summary: Language Server Protocol (LSP) implementation for Workflow Definition Language (WDL)
Home-page: https://github.com/broadinstitute/wdl-ide
Author: Broad Institute
License: BSD 3-clause "New" or "Revised" License
Classifier: Development Status :: 3 - Alpha
Classifier: Topic :: Scientific/Engineering :: Bio-Informatics
Classifier: Topic :: Software Development :: Interpreters
Classifier: License :: OSI Approved :: BSD License
Classifier: Operating System :: OS Independent
Classifier: Programming Language :: Python :: 3 :: Only
Classifier: Programming Language :: Python :: 3.8
Requires-Python: >=3.8
Requires-Dist: cromwell-tools >=2.4.1
Requires-Dist: miniwdl >=1.11.1
Requires-Dist: pygls >=1.3.1
